{
  "_IMPORTANTE": "NON USARE MAI SCRIPT AUTOMATICI PER RISOLVERE QUESTI ERRORI. Ogni errore deve essere analizzato e risolto manualmente attraverso il ragionamento. Non creare o eseguire script di risoluzione automatica.",
  "_DIRECTIVE": "ALWAYS use manual reasoning to fix each error. NEVER use automated scripts or batch fixes.",
  "groupNumber": 2,
  "totalErrors": 13,
  "files": [
    {
      "file": "components/cameriere/ActiveOrdersUnavailableModal.tsx",
      "errorCount": 6,
      "errors": [
        {
          "line": 68,
          "col": 55,
          "code": "TS2339",
          "message": "Property 'danger' does not exist on type '{ primary: string; primaryHover: string; primaryText: string; outlineBg: string; outlineBorder: string; outlineText: string; outlineHover: string; success: string; successHover: string; successText: string; }'."
        },
        {
          "line": 69,
          "col": 51,
          "code": "TS2339",
          "message": "Property 'danger' does not exist on type '{ primary: string; primaryHover: string; primaryText: string; outlineBg: string; outlineBorder: string; outlineText: string; outlineHover: string; success: string; successHover: string; successText: string; }'."
        },
        {
          "line": 75,
          "col": 105,
          "code": "TS2339",
          "message": "Property 'danger' does not exist on type '{ primary: string; primaryHover: string; primaryText: string; outlineBg: string; outlineBorder: string; outlineText: string; outlineHover: string; success: string; successHover: string; successText: string; }'."
        },
        {
          "line": 103,
          "col": 44,
          "code": "TS2339",
          "message": "Property 'danger' does not exist on type '{ primary: string; primaryHover: string; primaryText: string; outlineBg: string; outlineBorder: string; outlineText: string; outlineHover: string; success: string; successHover: string; successText: string; }'."
        },
        {
          "line": 153,
          "col": 54,
          "code": "TS2339",
          "message": "Property 'danger' does not exist on type '{ primary: string; primaryHover: string; primaryText: string; outlineBg: string; outlineBorder: string; outlineText: string; outlineHover: string; success: string; successHover: string; successText: string; }'."
        },
        {
          "line": 201,
          "col": 57,
          "code": "TS2339",
          "message": "Property 'danger' does not exist on type '{ primary: string; primaryHover: string; primaryText: string; outlineBg: string; outlineBorder: string; outlineText: string; outlineHover: string; success: string; successHover: string; successText: string; }'."
        }
      ]
    },
    {
      "file": "lib/actions/richiedi-aiuto.ts",
      "errorCount": 3,
      "errors": [
        {
          "line": 43,
          "col": 13,
          "code": "TS2304",
          "message": "Cannot find name 'sendSSEUpdate'."
        },
        {
          "line": 50,
          "col": 15,
          "code": "TS2304",
          "message": "Cannot find name 'sendSSEUpdate'."
        },
        {
          "line": 57,
          "col": 15,
          "code": "TS2304",
          "message": "Cannot find name 'sendSSEUpdate'."
        }
      ]
    },
    {
      "file": "app/api/admin/users/route.ts",
      "errorCount": 1,
      "errors": [
        {
          "line": 445,
          "col": 9,
          "code": "TS2353",
          "message": "Object literal may only specify known properties, and 'oldData' does not exist in type 'Without<AuditLogCreateInput, AuditLogUncheckedCreateInput> & AuditLogUncheckedCreateInput'."
        }
      ]
    },
    {
      "file": "app/cameriere/nuova-ordinazione/page.tsx",
      "errorCount": 1,
      "errors": [
        {
          "line": 112,
          "col": 19,
          "code": "TS2503",
          "message": "Cannot find namespace 'JSX'."
        }
      ]
    },
    {
      "file": "app/gestione-ordini/page-wrapper.tsx",
      "errorCount": 1,
      "errors": [
        {
          "line": 123,
          "col": 11,
          "code": "TS2719",
          "message": "Type 'OrdinazioneCompleta[]' is not assignable to type 'OrdinazioneCompleta[]'. Two different types with this name exist, but they are unrelated."
        }
      ]
    },
    {
      "file": "lib/utils/error-handlers.ts",
      "errorCount": 1,
      "errors": [
        {
          "line": 35,
          "col": 3,
          "code": "TS2304",
          "message": "Cannot find name 'showToast'."
        }
      ]
    }
  ]
}